djtagspecs/__init__.py
djtagspecs/__main__.py
djtagspecs/_typing.py
djtagspecs/catalog.py
djtagspecs/introspect.py
djtagspecs/models.py
djtagspecs/py.typed
djtagspecs-0.6.0.dist-info/WHEEL
djtagspecs-0.6.0.dist-info/entry_points.txt
djtagspecs-0.6.0.dist-info/METADATA
djtagspecs-0.6.0.dist-info/RECORD
