Metadata-Version: 2.3
Name: djtagspecs
Version: 0.6.0
Summary: Specification, schema, and CLI tooling for Django template TagSpecs
Author: Josh Thomas
Author-email: Josh Thomas <josh@joshthomas.dev>
License:                               Apache License
Requires-Dist: django>=4.2
Requires-Dist: pydantic>=2.11.9
Requires-Dist: rich>=14.2.0
Requires-Dist: tomli>=2.0.1 ; python_full_version < '3.11'
Requires-Dist: tomli-w>=1.0.0
Requires-Dist: typer>=0.19.1
Requires-Python: >=3.10
Project-URL: Documentation, https://github.com/joshuadavidthomas/djtagspecs#README
Project-URL: Issues, https://github.com/joshuadavidthomas/djtagspecs/issues
Project-URL: Source, https://github.com/joshuadavidthomas/djtagspecs
